{
    "climbers": [
        {
            "uuid" : "00000",
            "firstName": "Travis",
            "lastName": "Thompson",
            "climbLength":"21.17",
            "routeMoves": {
                "leftHand":
                    {"0": "01", "0.18": "", "1.01": "03", "6.14":"", "7.08":"07", "13.11":"", "13.18":"09", "19.07":"", "19.21":"12"}
                ,
                "rightHand":
                    {"0": "01", "3.14": "", "4.00": "04", "9.18":"", "10.05":"08", "17.02":"", "17.10":"10", "21.08":"", "21.17":"12"}
                ,
                "leftFoot": 
                    {"0": "f01", "2.11": "", "5.01":"01", "8.23":"", "11.03":"05", "18.07":"", "18.18":"06"}
                ,
                "rightFoot": 
                    {"0": "f02", "1.05": "", "2.02": "f05", "5.09":"", "8.14":"03", "11.15":"", "12.20":"f07", "14.16":"", "15.10":"f10", "20.14":""}
            }
        },

        {
            "uuid" : "00001",
            "firstName": "Colby",
            "lastName": "Frechette",
            "routeMoves": {
                "leftHand":
                    {"0.00":"01"}
                ,
                "rightHand":
                    {"0.00":"01"}
                ,
                "leftFoot": 
                    {}
                ,
                "rightFoot": 
                    {}
            }
        },

        {
            "uuid" : "00002",
            "firstName": "Jon",
            "lastName": "Aronoff",
            "routeMoves": {
                "leftHand":
                     {"0.00":"01"}
                ,
                "rightHand":
                    {"0.00":"01"}
                ,
                "leftFoot": 
                    {}
                ,
                "rightFoot": 
                    {}
            }
        },

        {
            "uuid" : "00003",
            "firstName": "Matt",
            "lastName": "Liliedahl",
            "routeMoves": {
                "leftHand":
                     {"0.00":"01", "0.06":"", "0.15":"03", "4.13":"", "5.02":"05", "8.08":"", "8.17":"07", "10.05":"", "10.17":"08", "12.04":"", "12.13":"09", "15.19":"", "16.07":"12"}
                ,
                "rightHand":
                    {"0.00":"01", "2.07":"", "2.18":"04", "6.08":"", "6.18":"06", "13.22":"", "14:10":"11", "17.16":"", "18.05":"12"}
                ,
                "leftFoot": 
                    {"0.00":"f01", "1.17":"", "3.17":"01", "5.15":"", "7.13":"02", "9.17":"", "11.12":"05", "14.15":"", "15.07":"07"}
                ,
                "rightFoot": 
                    {"0.00":"", "1.11":"f03", "3.22":"", "5.19":"01", "7.08":"", "9.13":"04", "11.17":"", "13.15":"06", "15.14":"", "17.04":"08"}
            }
        }
    ]
   
}